{
    "1250141995243143270": {
        "view_channel": true,
        "send_messages": false,
        "read_message_history": true
    },
    "1252701676712890369": {
        "view_channel": true,
        "send_messages": false,
        "read_message_history": true
    },
    "1256386441068417104": {
        "view_channel": true,
        "send_messages": false,
        "read_message_history": true
    },
    "1262610008848338964": {
        "view_channel": true,
        "send_messages": false,
        "read_message_history": true
    },
    "1250145163888824371": {
        "view_channel": true,
        "send_messages": true,
        "read_message_history": true
    },
    "1263997907908956223": {
        "view_channel": true,
        "send_messages": false,
        "read_message_history": true
    },
    "1250144135588085800": {
        "view_channel": true,
        "send_messages": false,
        "read_message_history": true
    },
    "1250144981939654837": {
        "view_channel": true,
        "send_messages": true,
        "read_message_history": true
    },
    "1250145535738904679": {
        "view_channel": true,
        "send_messages": true,
        "read_message_history": true
    },
    "1250931527005634684": {
        "view_channel": true,
        "send_messages": true,
        "read_message_history": true
    },
    "1250144108656197824": {
        "view_channel": true,
        "send_messages": true,
        "read_message_history": true
    }
}

1250189218659958886